LICENSE
kerykeion/__init__.py
kerykeion/aspects/__init__.py
kerykeion/aspects/aspects_utils.py
kerykeion/aspects/natal_aspects.py
kerykeion/aspects/synastry_aspects.py
kerykeion/astrological_subject.py
kerykeion/charts/__init__.py
kerykeion/charts/charts_utils.py
kerykeion/charts/draw_planets.py
kerykeion/charts/kerykeion_chart_svg.py
kerykeion/charts/templates/aspect_grid_only.xml
kerykeion/charts/templates/chart.xml
kerykeion/charts/templates/wheel_only.xml
kerykeion/charts/themes/classic.css
kerykeion/charts/themes/dark-high-contrast.css
kerykeion/charts/themes/dark.css
kerykeion/charts/themes/light.css
kerykeion/enums.py
kerykeion/ephemeris_data.py
kerykeion/fetch_geonames.py
kerykeion/kr_types/__init__.py
kerykeion/kr_types/chart_types.py
kerykeion/kr_types/kerykeion_exception.py
kerykeion/kr_types/kr_literals.py
kerykeion/kr_types/kr_models.py
kerykeion/kr_types/settings_models.py
kerykeion/relationship_score/__init__.py
kerykeion/relationship_score/relationship_score.py
kerykeion/relationship_score/relationship_score_factory.py
kerykeion/report.py
kerykeion/settings/__init__.py
kerykeion/settings/kerykeion_settings.py
kerykeion/settings/kr.config.json
kerykeion/sweph/README.md
kerykeion/sweph/seas_18.se1
kerykeion/utilities.py
kerykeion_json-1.0.1.dist-info/LICENSE
kerykeion_json-1.0.1.dist-info/METADATA
kerykeion_json-1.0.1.dist-info/WHEEL
kerykeion_json-1.0.1.dist-info/entry_points.txt
kerykeion_json-1.0.1.dist-info/RECORD
