Metadata-Version: 2.1
Name: kerykeion-json
Version: 1.0.1
Summary: A python library for astrology.
Home-page: https://www.kerykeion.net/
License: AGPL-3.0
Keywords: astrology,ephemeris,astrology library,birtchart,svg,zodiac,zodiac-sing,astronomical-algorithms,synastry,astrology-calculator
Author: Giacomo Battaglia
Author-email: kerykeion.astrology@gmail.com
Requires-Python: >=3.9,<4.0
Classifier: Development Status :: 5 - Production/Stable
Classifier: Intended Audience :: Developers
Classifier: Intended Audience :: Information Technology
Classifier: License :: OSI Approved :: GNU Affero General Public License v3
Classifier: License :: OSI Approved :: GNU General Public License (GPL)
Classifier: Operating System :: OS Independent
Classifier: Programming Language :: Python :: 3
Classifier: Programming Language :: Python :: 3.9
Classifier: Programming Language :: Python :: 3.10
Classifier: Programming Language :: Python :: 3.11
Classifier: Programming Language :: Python :: 3.12
Classifier: Programming Language :: Python :: 3.13
Classifier: Programming Language :: Python :: 3 :: Only
Classifier: Topic :: Scientific/Engineering :: Astronomy
Classifier: Topic :: Software Development
Classifier: Topic :: Software Development :: Libraries
Classifier: Topic :: Software Development :: Libraries :: Python Modules
Classifier: Typing :: Typed
Requires-Dist: pydantic (>=2.5,<3.0)
Requires-Dist: pyswisseph (>=2.10.3.1,<3.0.0.0)
Requires-Dist: pytz (>=2022.7,<2023.0)
Requires-Dist: requests (>=2.32.3,<3.0.0)
Requires-Dist: requests-cache (>=1.2.1,<2.0.0)
Requires-Dist: scour (>=0.38.2,<0.39.0)
Requires-Dist: terminaltables (>=3.1.10,<4.0.0)
Project-URL: Repository, https://github.com/Ugur-Atakan/kerykeion-json
